{"model":{"sets":[{"name":"model1","orientationType":"q","positions":[[-4,0,0],[-3,0,0],[-2,0,0],[-1,0,0],[0,0,0],[1,0,0],[2,0,0],[3,0,0],[4,0,0],[0,-4,0],[0,-3,0],[0,-2,0],[0,-1,0],[0,1,0],[0,2,0],[0,3,0],[0,4,0]],"orientations":[[0.707,-0.707,0,0],[0.851,-0.526,0,0],[0.924,-0.383,0,0],[0.973,-0.23,0,0],[1,0,0,0],[0.973,0.23,0,0],[0.924,0.383,0,0],[0.851,0.526,0,0],[0.707,0.707,0,0],[0.707,0,0.707,0],[0.851,0,0.526,0],[0.924,0,0.383,0],[0.973,0,0.23,0],[0.973,0,-0.23,0],[0.924,0,-0.383,0],[0.851,0,-0.526,0],[0.707,0,-0.707,0]]}]},"state":{"reference":{"boundingShapeEnabled":false,"activeShape":"box","showAxes":true,"showGrid":false,"gridColour":{"r":255,"g":0,"b":0},"size":18},"ambientLight":{"ambientLightColour":{"r":255,"g":240,"b":255,"i":54},"backgroundColour":{"r":255,"g":255,"b":255}},"pointLight":{"reset":0,"active":"point","enabled":true,"colour":{"r":255,"g":255,"b":255,"i":60},"position":{"x":5,"y":0,"z":5}},"directionalLight":{"reset":0,"active":"directional","enabled":true,"colour":{"r":255,"g":255,"b":255,"i":50},"position":{"x":-5,"y":0,"z":-5}},"camera":{"rotating":false,"type":"perspective","lookAt":{"x":0,"y":0,"z":0},"LOD":4},"slicing":{"clipIntersection":false,"helpers":[false,false,false],"x":[-50,50],"y":[-50,50],"z":[-50,50]},"model":{"active":0,"reset":0,"sets":["Set A"],"configurations":[{"title":"Set A","shape":"Ellipsoid","parameters":{"names":["X","Y","Z"],"vals":[0.5,0.5,1.5]},"colour":{"r":255,"g":98,"b":255},"shininess":100,"colourFromDirector":true,"displayAsWireframe":true}]}}}